extendparser/__init__.py
extendparser/environ.py
extendparser/get.py
extendparser/include.py
extendparser/py.typed
extendparser-0.3.1.data/data/share/doc/extendparser/AUTHORS
extendparser-0.3.1.data/data/share/doc/extendparser/CONTRIBUTION.rst
extendparser-0.3.1.data/data/share/doc/extendparser/COPYING
extendparser-0.3.1.data/data/share/doc/extendparser/ChangeLog
extendparser-0.3.1.data/data/share/doc/extendparser/README.rst
extendparser-0.3.1.dist-info/AUTHORS
extendparser-0.3.1.dist-info/COPYING
extendparser-0.3.1.dist-info/METADATA
extendparser-0.3.1.dist-info/WHEEL
extendparser-0.3.1.dist-info/top_level.txt
extendparser-0.3.1.dist-info/RECORD
