Metadata-Version: 2.1
Name: extendparser
Version: 0.3.1
Summary: ExtendParser extend stanrad ConfigParser for some functionality.
Home-page: https://github.com/ondratu/extendparser
Author: Ondřej Tůma
Author-email: mcbig@zeropage.cz
License: BSD
Platform: UNKNOWN
Classifier: Development Status :: 5 - Production/Stable
Classifier: Intended Audience :: Developers
Classifier: License :: OSI Approved :: BSD License
Classifier: Operating System :: OS Independent
Classifier: Programming Language :: Python :: 3
Classifier: Topic :: Software Development :: Libraries
